fast_protocol.py
fast_protocol-1.0.1.dist-info/LICENSE
fast_protocol-1.0.1.dist-info/WHEEL
fast_protocol-1.0.1.dist-info/METADATA
fast_protocol-1.0.1.dist-info/RECORD
