Metadata-Version: 2.1
Name: fast-protocol
Version: 1.0.1
Summary: A very simple Python module to declare protocols for checking if objects provide the desired interface.
Home-page: https://github.com/ZechCodes/fast-protocol
License: MIT
Keywords: type,protocol,match,checking,interface
Author: Zech Zimmerman
Author-email: hi@zech.codes
Requires-Python: >=3.7,<4.0
Classifier: Development Status :: 5 - Production/Stable
Classifier: Intended Audience :: Developers
Classifier: License :: OSI Approved :: MIT License
Classifier: Programming Language :: Python
Classifier: Programming Language :: Python :: 3
Classifier: Programming Language :: Python :: 3 :: Only
Classifier: Programming Language :: Python :: 3.10
Classifier: Programming Language :: Python :: 3.11
Classifier: Programming Language :: Python :: 3.12
Classifier: Programming Language :: Python :: 3.7
Classifier: Programming Language :: Python :: 3.8
Classifier: Programming Language :: Python :: 3.9
Classifier: Topic :: Software Development
Classifier: Topic :: Utilities
Classifier: Typing :: Typed
Project-URL: Documentation, https://github.com/ZechCodes/fast-protocol
Project-URL: Repository, https://github.com/ZechCodes/fast-protocol
